linefit_bind.pypy38-pp73-darwin.so
linefit/__init__.py
linefit-1.1.0.dist-info/RECORD
linefit-1.1.0.dist-info/WHEEL
linefit-1.1.0.dist-info/METADATA
linefit-1.1.0.dist-info/licenses/LICENSE
