Metadata-Version: 2.1
Name: linefit
Version: 1.1.0
Summary: linefit ground segmentation algorithm Python bindings
Author-Email: Qingwen Zhang <qingwen@kth.se>
Classifier: License :: OSI Approved :: BSD License
Classifier: Programming Language :: Python :: 3
Classifier: Programming Language :: Python :: 3.8
Classifier: Programming Language :: Python :: 3.9
Classifier: Programming Language :: Python :: 3.10
Classifier: Programming Language :: Python :: 3.11
Classifier: Programming Language :: Python :: 3.12
Classifier: Programming Language :: Python :: 3.13
Project-URL: urls, https://github.com/Kin-Zhang/linefit
Requires-Python: >=3.8
Requires-Dist: numpy
